{
  "hash": "283e2fef4b657baa01ee3168fa06bcae",
  "result": {
    "markdown": "---\ntitle: \"Overview of indicators\"\n---\n\n::: {.cell}\n\n:::\n\n\n## Reporting rates\n\n::: panel-tabset\n## MOH 515\n\n## MOH 705A\n\n## MOH 705B\n:::\n\n------------------------------------------------------------------------\n\n## Malaria trends\n\n::: panel-tabset\n## Under 5\n\nTotal number of <span style='color:#bdbdbd'>**suspected**</span>, <span style='color:#7570b3'>**tested**</span>, and <span style='color:#d95f02'>**confirmed**</span> malaria cases by sub-county.\n\n\n::: {.cell}\n::: {.cell-output-display}\n![](indicators_files/figure-html/generate-indicators-u5-1.png){width=1152}\n:::\n:::\n\n\n## Over 5\n\nTotal number of <span style='color:#bdbdbd'>**suspected**</span>, <span style='color:#7570b3'>**tested**</span>, and <span style='color:#d95f02'>**confirmed**</span> malaria cases by sub-county.\n\n\n::: {.cell}\n::: {.cell-output-display}\n![](indicators_files/figure-html/generate-indicators-o5-1.png){width=1152}\n:::\n:::\n\n:::\n\n------------------------------------------------------------------------\n\n## Net ownership and usage\n::: panel-tabset\n\n## Net ownership\nProportion of people who own a net over the study period.\n\n::: {.cell}\n::: {.cell-output-display}\n![](indicators_files/figure-html/generate-indicators-net-ownership-1.png){width=1152}\n:::\n:::\n\n\n## Net usage\nProportion of people who slept under a net the previous night over the study period.\n\n::: {.cell}\n::: {.cell-output-display}\n![](indicators_files/figure-html/generate-indicators-net-usage-1.png){width=1152}\n:::\n:::\n\n:::",
    "supporting": [
      "indicators_files"
    ],
    "filters": [
      "rmarkdown/pagebreak.lua"
    ],
    "includes": {},
    "engineDependencies": {},
    "preserve": {},
    "postProcess": true
  }
}